2x2/bilg org/odev3/czum/RiscV_SingleCycle.v
`timescale 1ns / 1ps
module RiscV_SingleCycle(
    input clk,
    input reset,
    output reg [31:0] pc,
    output reg [31:0] alu_result,
    output [31:0] write_data,
    input [31:0] read_data
);

    // Define memory
    reg [31:0] memory[0:1023]; // 1K words of memory
    reg [31:0] instruction_memory[0:255]; // 256 words of instruction memory

    // Register and next PC logic
    reg [31:0] next_pc;
    reg [31:0] registers[0:31];

    // Decode fields from instruction
    wire [31:0] instruction = instruction_memory[pc >> 2]; // Fetch instruction based on PC
    wire [6:0] opcode = instruction[6:0];
    wire [4:0] rd = instruction[11:7];
    wire [4:0] rs1 = instruction[19:15];
    wire [4:0] rs2 = instruction[24:20];
    wire [2:0] funct3 = instruction[14:12];
    wire [6:0] funct7 = instruction[31:25];
    wire [31:0] rs1_data = registers[rs1];
    wire [31:0] rs2_data = registers[rs2];

    // Immediate value processing
    wire signed [31:0] imm_i = {{20{instruction[31]}}, instruction[31:20]};
    wire signed [31:0] imm_s = {{20{instruction[31]}}, instruction[31:25], instruction[11:7]};
    wire [31:0] sign_extended_imm = (opcode == 7'b0000011 || opcode == 7'b0100011) ? imm_i : imm_s;

    always @(posedge clk or posedge reset) begin
        if (reset) begin
            pc <= 0;
        end else begin
            pc <= next_pc;
        end
    end

    // ALU operation
    reg [31:0] alu_out;
    always @(*) begin
        case (opcode)
            7'b0110011: // R-type operations
                case (funct3)
                    3'b000: alu_out = (funct7 == 7'b0000000) ? rs1_data + rs2_data : rs1_data - rs2_data;
                    3'b101: 
                    if (funct7 == 7'b0100000) begin
                        alu_out = $signed(rs1_data) >>> rs2_data[4:0]; // Arithmetic shift right
                    end else begin
                        alu_out = rs1_data >> rs2_data[4:0]; // Logical shift right
                    end
                    3'b110: alu_out = rs1_data | rs2_data;
                    3'b111: alu_out = rs1_data & rs2_data;
                    3'b010: alu_out = ($signed(rs1_data) < $signed(rs2_data)) ? 1 : 0;
                endcase
            7'b1101111: // JAL
                begin
                    next_pc = pc + {{12{instruction[31]}}, instruction[19:12], instruction[20], instruction[30:21], 1'b0};
                    registers[rd] <= next_pc;
                end
            7'b1100011: // BEQ
                if (funct3 == 3'b000 && rs1_data == rs2_data) begin
                    next_pc = pc + {{20{instruction[31]}}, instruction[7], instruction[30:25], instruction[11:8], 1'b0};
                end else begin
                    next_pc = pc + 4;
                end
            7'b0000011: alu_out = rs1_data + sign_extended_imm; // LW
            7'b0100011: alu_out = rs1_data + sign_extended_imm; // SW
            7'b0010011: // I-type ALU operations
                case (funct3)
                    3'b000: alu_out = rs1_data + sign_extended_imm;
                    3'b110: alu_out = rs1_data | sign_extended_imm;
                    3'b111: alu_out = rs1_data & sign_extended_imm;
                    3'b010: alu_out = ($signed(rs1_data) < $signed(sign_extended_imm)) ? 1 : 0;
                endcase
        endcase
    end

    // Update alu_result on clock edge to capture the computed ALU output
    always @(posedge clk) begin
        alu_result <= alu_out;
    end

    // Write data to registers and handle load/store
    assign write_data = registers[rd];
    always @(posedge clk) begin
        if (!reset && rd != 0) begin
            if (opcode == 7'b0000011) // LW
                registers[rd] <= memory[alu_out[9:0]]; // Read from memory
            else if (opcode != 7'b0100011) // Not SW
                registers[rd] <= alu_out;
        end
        if (opcode == 7'b0100011) // SW
            memory[alu_out[9:0]] <= rs2_data; // Write to memory
    end

    // Update next_pc
always @(posedge clk or posedge reset) begin
    if (reset) begin
        next_pc <= 0;
    end else begin
        case (opcode)
            7'b1101111: // JAL
                begin
                    next_pc <= pc + {{12{instruction[31]}}, instruction[19:12], instruction[20], instruction[30:21], 1'b0};
                end
            7'b1100011: // BEQ
                begin
                    if (funct3 == 3'b000 && rs1_data == rs2_data) begin
                        next_pc <= pc + {{20{instruction[31]}}, instruction[7], instruction[30:25], instruction[11:8], 1'b0};
                    end else begin
                        next_pc <= pc + 4;
                    end
                end
            default:
                next_pc <= pc + 4; // Default case for other instructions
        endcase
    end
end


    always @(posedge clk) begin
        //$display("Time: %t, PC: %d, Next PC: %d, Opcode: %b, Funct3: %b, RS1 Data: %d, RS2 Data: %d, ALU Result: %d, Reg 1: %d, reg 2 : %d, Reg 6: %d, reg 7 : %d",
          //       $time, pc, next_pc, opcode, funct3, rs1_data, rs2_data, alu_result, registers[1], registers[2],registers[6], registers[7]);
        $display("instruction: %d, pc: %d, nextpc: %d, Reg 1: %d, reg 2 : %d, Reg 6: %d, reg 7 : %d",
                 instruction, pc, next_pc, registers[1], registers[2],registers[6], registers[7]);
    end

   

endmodule

2x2/bilg org/odev3/czum/TestBench.v
`timescale 1ns / 1ps
`include "RiscV_SingleCycle.v"
module TestBench;
    reg clk = 0;
    reg reset = 1;

    wire [31:0] pc;
    wire [31:0] alu_result;
    wire [31:0] write_data;
    wire [31:0] read_data = 32'b0;

    RiscV_SingleCycle uut(
        .clk(clk),
        .reset(reset),
        .pc(pc),
        .alu_result(alu_result),
        .write_data(write_data),
        .read_data(read_data)
    );

    always #10 clk = !clk;

    initial begin
        $dumpfile("processor_sim.vcd");
        $dumpvars(0, TestBench);

        // Assert reset
        reset = 1;
        #20; // Hold reset for 100ns
        reset = 0;

        // Initialize memory
        #20;
        uut.memory[0] = 3;    uut.memory[1] = 7;    uut.memory[2] = 2;    uut.memory[3] = 6;
        uut.memory[4] = 5;    uut.memory[5] = 4;    uut.memory[6] = 1;    uut.memory[7] = 1000;
        uut.memory[8] = 999;  uut.memory[9] = 25;   uut.memory[10] = 90;  uut.memory[11] = 100;
        uut.memory[12] = 30;  uut.memory[13] = 20;  uut.memory[14] = 10;  uut.memory[15] = 200;
        uut.memory[16] = 3300; uut.memory[17] = 250; uut.memory[18] = 12;  uut.memory[19] = 75;
        uut.memory[20] = 17;  uut.memory[21] = 13;  uut.memory[22] = 18;  uut.memory[23] = 14;
        uut.memory[24] = 15;  uut.memory[25] = 16;  uut.memory[26] = 19;  uut.memory[27] = 1;
        uut.memory[28] = 2;   uut.memory[29] = 9;   uut.memory[30] = 6;   uut.memory[31] = 5;
        uut.memory[32] = 8;   uut.memory[33] = 10;  uut.memory[34] = 12;  uut.memory[35] = 4;
        uut.memory[36] = 0;   uut.memory[37] = 3;   uut.memory[38] = 11;  uut.memory[39] = 7;

        uut.registers[0] = 0;
        uut.registers[1] = 0;
        uut.registers[2] = 80;
        uut.registers[3] = 160;
        uut.registers[4] = 80;
    
        // load instructions into the instruction memory
        uut.instruction_memory[0] = 32'h00000013;
        uut.instruction_memory[1] = 32'h02408663;
        uut.instruction_memory[2] = 32'h0000a303;
        uut.instruction_memory[3] = 32'h00012383;
        uut.instruction_memory[4] = 32'h007383b3;
        uut.instruction_memory[5] = 32'h007383b3;
        uut.instruction_memory[6] = 32'h007383b3;
        uut.instruction_memory[7] = 32'h007184b3;
        uut.instruction_memory[8] = 32'h0064a023;
        uut.instruction_memory[9] = 32'h00408093;
        uut.instruction_memory[10] = 32'h00110113;
        uut.instruction_memory[11] = 32'hfd9ff56f;

        #30000;

        // final states
        $display("Time: %t", $time);
        $display("PC: %d", pc);
        $display("hmm: %d %d %d %d %d", uut.memory[40], uut.memory[45], uut.registers[0], uut.registers[1], uut.registers[2], uut.registers[3], uut.registers[4]);
        $finish;
    end
endmodule

//iverilog -o testbench_output RiscV_SingleCycle.v TestBench.v
//vvp testbench_output

2x2/bilg org/odev3/czum/processor_sim.vcd
$date
	Sun May 19 20:44:05 2024
$end
$version
	Icarus Verilog
$end
$timescale
	1ps
$end
$scope module TestBench $end
$var wire 32 ! read_data [31:0] $end
$var wire 32 " write_data [31:0] $end
$var wire 32 # pc [31:0] $end
$var wire 32 $ alu_result [31:0] $end
$var reg 1 % clk $end
$var reg 1 & reset $end
$scope module uut $end
$var wire 1 % clk $end
$var wire 32 ' instruction [31:0] $end
$var wire 32 ( read_data [31:0] $end
$var wire 1 & reset $end
$var wire 32 ) rs1_data [31:0] $end
$var wire 32 * rs2_data [31:0] $end
$var wire 32 + write_data [31:0] $end
$var wire 32 , sign_extended_imm [31:0] $end
$var wire 5 - rs2 [4:0] $end
$var wire 5 . rs1 [4:0] $end
$var wire 5 / rd [4:0] $end
$var wire 7 0 opcode [6:0] $end
$var wire 32 1 imm_s [31:0] $end
$var wire 32 2 imm_i [31:0] $end
$var wire 7 3 funct7 [6:0] $end
$var wire 3 4 funct3 [2:0] $end
$var reg 32 5 alu_out [31:0] $end
$var reg 32 6 alu_result [31:0] $end
$var reg 32 7 next_pc [31:0] $end
$var reg 32 8 pc [31:0] $end
$upscope $end
$upscope $end
$enddefinitions $end
$comment Show the parameter values. $end
$dumpall
$end
#0
$dumpvars
b0 8
b0 7
bx 6
bx 5
bx 4
bx 3
bx 2
bx 1
bx 0
bx /
bx .
bx -
bx ,
bx +
bx *
bx )
b0 (
bx '
1&
0%
bx $
b0 #
bx "
b0 !
$end
#10000
1%
#20000
0%
0&
#30000
b100 7
1%
#40000
b0 5
b0 ,
b10011 0
b0 "
b0 +
b0 /
b0 )
b0 .
b0 *
b0 -
b0 4
b0 3
b0 2
b0 1
0%
b10011 '
#50000
b1000 7
b101100 ,
b1100011 0
bx "
bx +
b1100 /
b1 .
b1010000 *
b100 -
b1 3
b100100 2
b101100 1
b10010000001000011001100011 '
b0 $
b0 6
b100 #
b100 8
1%
#60000
0%
#70000
b0 5
b0 ,
b11 0
b110 /
b0 *
b0 -
b10 4
b0 3
b0 2
b110 1
b1100 7
b1010001100000011 '
bx "
bx +
b1000 #
b1000 8
1%
#80000
0%
#90000
b1010000 5
b111 /
b1010000 )
b10 .
b111 1
b10010001110000011 '
bx "
bx +
b1100 #
b1100 8
1%
#100000
0%
#110000
b1010000 $
b1010000 6
b10000 7
1%
#120000
0%
#130000
bx 5
b111 ,
b110011 0
bx )
b111 .
bx *
b111 -
b0 4
b111 2
b11100111000001110110011 '
b10000 #
b10000 8
1%
#140000
0%
#150000
bx $
bx 6
b10100 7
1%
#160000
0%
#170000
b10100 #
b10100 8
1%
#180000
0%
#190000
b11000 7
1%
#200000
0%
#210000
b11000 #
b11000 8
1%
#220000
0%
#230000
b11100 7
1%
#240000
0%
#250000
b1001 ,
b1001 /
b10100000 )
b11 .
b1001 1
b11100011000010010110011 '
b11100 #
b11100 8
1%
#260000
0%
#270000
b100000 7
1%
#280000
0%
#290000
b110 ,
b100011 0
b0 "
b0 +
b0 /
bx )
b1001 .
b11 *
b110 -
b10 4
b110 2
b0 1
b11001001010000000100011 '
b100000 #
b100000 8
1%
#300000
0%
#310000
b100100 7
1%
#320000
0%
#330000
b1 5
b1 ,
b10011 0
b1 /
b0 )
b1 .
b1010000 *
b100 -
b0 4
b100 2
b1 1
b10000001000000010010011 '
b100100 #
b100100 8
1%
#340000
0%
#350000
b10 5
b1 )
b1 "
b1 +
b1 $
b1 6
b101000 7
1%
#360000
0%
#370000
b10 ,
b10 /
b10 .
b10 *
b1 -
b1 2
b10 1
b1010010 5
b100010000000100010011 '
b10 $
b10 6
b1010000 )
b1010000 "
b1010000 +
b101000 #
b101000 8
1%
#380000
0%
#390000
b1010100 5
b1010010 )
b1010010 "
b1010010 +
b1010010 $
b1010010 6
b101100 7
1%
#400000
0%
#410000
b100 7
b11111111111111111111111111001010 ,
b1101111 0
b1010 /
b11111 .
bx *
b11001 -
b111 4
b1111110 3
b11111111111111111111111111011001 2
b11111111111111111111111111001010 1
b1010110 5
b11111101100111111111010101101111 '
b1010100 $
b1010100 6
bx )
b100 "
b100 +
b101100 #
b101100 8
1%
#420000
0%
#430000
b101100 ,
b1100011 0
b1100 /
b10 )
b1 .
b1010000 *
b100 -
b0 4
b1 3
b100100 2
b101100 1
b1000 7
b10010000001000011001100011 '
b0 "
b0 +
b1010110 $
b1010110 6
b100 #
b100 8
1%
#440000
0%
#450000
b10 5
b0 ,
b11 0
b110 /
b0 *
b0 -
b10 4
b0 3
b0 2
b110 1
b1100 7
b1010001100000011 '
b11 "
b11 +
b1000 #
b1000 8
1%
#460000
0%
#470000
b1010100 5
b111 /
b1010100 )
b10 .
b111 1
b10010001110000011 '
bx "
bx +
b10 $
b10 6
b1100 #
b1100 8
1%
#480000
0%
#490000
b1010100 $
b1010100 6
b10000 7
1%
#500000
0%
#510000
bx 5
b111 ,
b110011 0
bx )
b111 .
bx *
b111 -
b0 4
b111 2
b11100111000001110110011 '
b10000 #
b10000 8
1%
#520000
0%
#530000
bx $
bx 6
b10100 7
1%
#540000
0%
#550000
b10100 #
b10100 8
1%
#560000
0%
#570000
b11000 7
1%
#580000
0%
#590000
b11000 #
b11000 8
1%
#600000
0%
#610000
b11100 7
1%
#620000
0%
#630000
b1001 ,
b1001 /
b10100000 )
b11 .
b1001 1
b11100011000010010110011 '
b11100 #
b11100 8
1%
#640000
0%
#650000
b100000 7
1%
#660000
0%
#670000
b110 ,
b100011 0
b0 "
b0 +
b0 /
bx )
b1001 .
b10 *
b110 -
b10 4
b110 2
b0 1
b11001001010000000100011 '
b100000 #
b100000 8
1%
#680000
0%
#690000
b100100 7
1%
#700000
0%
#710000
b11 5
b1 ,
b10011 0
b10 "
b10 +
b1 /
b10 )
b1 .
b1010000 *
b100 -
b0 4
b100 2
b1 1
b10000001000000010010011 '
b100100 #
b100100 8
1%
#720000
0%
#730000
b100 5
b11 $
b11 6
b11 )
b11 "
b11 +
b101000 7
1%
#740000
0%
#750000
b10 ,
b10 /
b10 .
b100 *
b1 -
b1 2
b10 1
b1010110 5
b100010000000100010011 '
b1010100 )
b1010100 "
b1010100 +
b100 $
b100 6
b101000 #
b101000 8
1%
#760000
0%
#770000
b1011000 5
b1010110 $
b1010110 6
b1010110 )
b1010110 "
b1010110 +
b101100 7
1%
#780000
0%
#790000
b100 7
b11111111111111111111111111001010 ,
b1101111 0
b1010 /
b11111 .
bx *
b11001 -
b111 4
b1111110 3
b11111111111111111111111111011001 2
b11111111111111111111111111001010 1
b1011010 5
b11111101100111111111010101101111 '
bx )
b100 "
b100 +
b1011000 $
b1011000 6
b101100 #
b101100 8
1%
#800000
0%
#810000
b101100 ,
b1100011 0
b1100 /
b100 )
b1 .
b1010000 *
b100 -
b0 4
b1 3
b100100 2
b101100 1
b1000 7
b10010000001000011001100011 '
b1011010 $
b1011010 6
b1010110 "
b1010110 +
b100 #
b100 8
1%
#820000
0%
#830000
b100 5
b0 ,
b11 0
b110 /
b0 *
b0 -
b10 4
b0 3
b0 2
b110 1
b1100 7
b1010001100000011 '
b10 "
b10 +
b1000 #
b1000 8
1%
#840000
0%
#850000
b1011000 5
b111 /
b1011000 )
b10 .
b111 1
b10010001110000011 '
b100 $
b100 6
bx "
bx +
b1100 #
b1100 8
1%
#860000
0%
#870000
b1011000 $
b1011000 6
b10000 7
1%
#880000
0%
#890000
bx 5
b111 ,
b110011 0
bx )
b111 .
bx *
b111 -
b0 4
b111 2
b11100111000001110110011 '
b10000 #
b10000 8
1%
#900000
0%
#910000
bx $
bx 6
b10100 7
1%
#920000
0%
#930000
b10100 #
b10100 8
1%
#940000
0%
#950000
b11000 7
1%
#960000
0%
#970000
b11000 #
b11000 8
1%
#980000
0%
#990000
b11100 7
1%
#1000000
0%
#1010000
b1001 ,
b1001 /
b10100000 )
b11 .
b1001 1
b11100011000010010110011 '
b11100 #
b11100 8
1%
#1020000
0%
#1030000
b100000 7
1%
#1040000
0%
#1050000
b110 ,
b100011 0
b0 "
b0 +
b0 /
bx )
b1001 .
b101 *
b110 -
b10 4
b110 2
b0 1
b11001001010000000100011 '
b100000 #
b100000 8
1%
#1060000
0%
#1070000
b100100 7
1%
#1080000
0%
#1090000
b101 5
b1 ,
b10011 0
b100 "
b100 +
b1 /
b100 )
b1 .
b1010000 *
b100 -
b0 4
b100 2
b1 1
b10000001000000010010011 '
b100100 #
b100100 8
1%
#1100000
0%
#1110000
b110 5
b101 )
b101 "
b101 +
b101 $
b101 6
b101000 7
1%
#1120000
0%
#1130000
b10 ,
b10 /
b10 .
b110 *
b1 -
b1 2
b10 1
b1011010 5
b100010000000100010011 '
b110 $
b110 6
b1011000 )
b1011000 "
b1011000 +
b101000 #
b101000 8
1%
#1140000
0%
#1150000
b1011100 5
b1011010 )
b1011010 "
b1011010 +
b1011010 $
b1011010 6
b101100 7
1%
#1160000
0%
#1170000
b100 7
b11111111111111111111111111001010 ,
b1101111 0
b1010 /
b11111 .
bx *
b11001 -
b111 4
b1111110 3
b11111111111111111111111111011001 2
b11111111111111111111111111001010 1
b1011110 5
b11111101100111111111010101101111 '
b1011100 $
b1011100 6
bx )
b100 "
b100 +
b101100 #
b101100 8
1%
#1180000
0%
#1190000
b101100 ,
b1100011 0
b1100 /
b110 )
b1 .
b1010000 *
b100 -
b0 4
b1 3
b100100 2
b101100 1
b1000 7
b10010000001000011001100011 '
b1011010 "
b1011010 +
b1011110 $
b1011110 6
b100 #
b100 8
1%
#1200000
0%
#1210000
b110 5
b0 ,
b11 0
b110 /
b0 *
b0 -
b10 4
b0 3
b0 2
b110 1
b1100 7
b1010001100000011 '
b101 "
b101 +
b1000 #
b1000 8
1%
#1220000
0%
#1230000
b1011100 5
b111 /
b1011100 )
b10 .
b111 1
b10010001110000011 '
bx "
bx +
b110 $
b110 6
b1100 #
b1100 8
1%
#1240000
0%
#1250000
b1011100 $
b1011100 6
b10000 7
1%
#1260000
0%
#1270000
bx 5
b111 ,
b110011 0
bx )
b111 .
bx *
b111 -
b0 4
b111 2
b11100111000001110110011 '
b10000 #
b10000 8
1%
#1280000
0%
#1290000
bx $
bx 6
b10100 7
1%
#1300000
0%
#1310000
b10100 #
b10100 8
1%
#1320000
0%
#1330000
b11000 7
1%
#1340000
0%
#1350000
b11000 #
b11000 8
1%
#1360000
0%
#1370000
b11100 7
1%
#1380000
0%
#1390000
b1001 ,
b1001 /
b10100000 )
b11 .
b1001 1
b11100011000010010110011 '
b11100 #
b11100 8
1%
#1400000
0%
#1410000
b100000 7
1%
#1420000
0%
#1430000
b110 ,
b100011 0
b0 "
b0 +
b0 /
bx )
b1001 .
b1 *
b110 -
b10 4
b110 2
b0 1
b11001001010000000100011 '
b100000 #
b100000 8
1%
#1440000
0%
#1450000
b100100 7
1%
#1460000
0%
#1470000
b111 5
b1 ,
b10011 0
b110 "
b110 +
b1 /
b110 )
b1 .
b1010000 *
b100 -
b0 4
b100 2
b1 1
b10000001000000010010011 '
b100100 #
b100100 8
1%
#1480000
0%
#1490000
b1000 5
b111 $
b111 6
b111 )
b111 "
b111 +
b101000 7
1%
#1500000
0%
#1510000
b10 ,
b10 /
b10 .
b1000 *
b1 -
b1 2
b10 1
b1011110 5
b100010000000100010011 '
b1011100 )
b1011100 "
b1011100 +
b1000 $
b1000 6
b101000 #
b101000 8
1%
#1520000
0%
#1530000
b1100000 5
b1011110 $
b1011110 6
b1011110 )
b1011110 "
b1011110 +
b101100 7
1%
#1540000
0%
#1550000
b100 7
b11111111111111111111111111001010 ,
b1101111 0
b1010 /
b11111 .
bx *
b11001 -
b111 4
b1111110 3
b11111111111111111111111111011001 2
b11111111111111111111111111001010 1
b1100010 5
b11111101100111111111010101101111 '
bx )
b100 "
b100 +
b1100000 $
b1100000 6
b101100 #
b101100 8
1%
#1560000
0%
#1570000
b101100 ,
b1100011 0
b1100 /
b1000 )
b1 .
b1010000 *
b100 -
b0 4
b1 3
b100100 2
b101100 1
b1000 7
b10010000001000011001100011 '
b1100010 $
b1100010 6
b1011110 "
b1011110 +
b100 #
b100 8
1%
#1580000
0%
#1590000
b1000 5
b0 ,
b11 0
b110 /
b0 *
b0 -
b10 4
b0 3
b0 2
b110 1
b1100 7
b1010001100000011 '
b1 "
b1 +
b1000 #
b1000 8
1%
#1600000
0%
#1610000
b1100000 5
b111 /
b1100000 )
b10 .
b111 1
b10010001110000011 '
b1000 $
b1000 6
bx "
bx +
b1100 #
b1100 8
1%
#1620000
0%
#1630000
b1100000 $
b1100000 6
b10000 7
1%
#1640000
0%
#1650000
bx 5
b111 ,
b110011 0
bx )
b111 .
bx *
b111 -
b0 4
b111 2
b11100111000001110110011 '
b10000 #
b10000 8
1%
#1660000
0%
#1670000
bx $
bx 6
b10100 7
1%
#1680000
0%
#1690000
b10100 #
b10100 8
1%
#1700000
0%
#1710000
b11000 7
1%
#1720000
0%
#1730000
b11000 #
b11000 8
1%
#1740000
0%
#1750000
b11100 7
1%
#1760000
0%
#1770000
b1001 ,
b1001 /
b10100000 )
b11 .
b1001 1
b11100011000010010110011 '
b11100 #
b11100 8
1%
#1780000
0%
#1790000
b100000 7
1%
#1800000
0%
#1810000
b110 ,
b100011 0
b0 "
b0 +
b0 /
bx )
b1001 .
b1111100111 *
b110 -
b10 4
b110 2
b0 1
b11001001010000000100011 '
b100000 #
b100000 8
1%
#1820000
0%
#1830000
b100100 7
1%
#1840000
0%
#1850000
b1001 5
b1 ,
b10011 0
b1000 "
b1000 +
b1 /
b1000 )
b1 .
b1010000 *
b100 -
b0 4
b100 2
b1 1
b10000001000000010010011 '
b100100 #
b100100 8
1%
#1860000
0%
#1870000
b1010 5
b1001 )
b1001 "
b1001 +
b1001 $
b1001 6
b101000 7
1%
#1880000
0%
#1890000
b10 ,
b10 /
b10 .
b1010 *
b1 -
b1 2
b10 1
b1100010 5
b100010000000100010011 '
b1010 $
b1010 6
b1100000 )
b1100000 "
b1100000 +
b101000 #
b101000 8
1%
#1900000
0%
#1910000
b1100100 5
b1100010 )
b1100010 "
b1100010 +
b1100010 $
b1100010 6
b101100 7
1%
#1920000
0%
#1930000
b100 7
b11111111111111111111111111001010 ,
b1101111 0
b1010 /
b11111 .
bx *
b11001 -
b111 4
b1111110 3
b11111111111111111111111111011001 2
b11111111111111111111111111001010 1
b1100110 5
b11111101100111111111010101101111 '
b1100100 $
b1100100 6
bx )
b100 "
b100 +
b101100 #
b101100 8
1%
#1940000
0%
#1950000
b101100 ,
b1100011 0
b1100 /
b1010 )
b1 .
b1010000 *
b100 -
b0 4
b1 3
b100100 2
b101100 1
b1000 7
b10010000001000011001100011 '
b1100010 "
b1100010 +
b1100110 $
b1100110 6
b100 #
b100 8
1%
#1960000
0%
#1970000
b1010 5
b0 ,
b11 0
b110 /
b0 *
b0 -
b10 4
b0 3
b0 2
b110 1
b1100 7
b1010001100000011 '
b1111100111 "
b1111100111 +
b1000 #
b1000 8
1%
#1980000
0%
#1990000
b1100100 5
b111 /
b1100100 )
b10 .
b111 1
b10010001110000011 '
bx "
bx +
b1010 $
b1010 6
b1100 #
b1100 8
1%
#2000000
0%
#2010000
b1100100 $
b1100100 6
b10000 7
1%
#2020000
0%
#2030000
bx 5
b111 ,
b110011 0
bx )
b111 .
bx *
b111 -
b0 4
b111 2
b11100111000001110110011 '
b10000 #
b10000 8
1%
#2040000
0%
#2050000
bx $
bx 6
b10100 7
1%
#2060000
0%
#2070000
b10100 #
b10100 8
1%
#2080000
0%
#2090000
b11000 7
1%
#2100000
0%
#2110000
b11000 #
b11000 8
1%
#2120000
0%
#2130000
b11100 7
1%
#2140000
0%
#2150000
b1001 ,
b1001 /
b10100000 )
b11 .
b1001 1
b11100011000010010110011 '
b11100 #
b11100 8
1%
#2160000
0%
#2170000
b100000 7
1%
#2180000
0%
#2190000
b110 ,
b100011 0
b0 "
b0 +
b0 /
bx )
b1001 .
b1011010 *
b110 -
b10 4
b110 2
b0 1
b11001001010000000100011 '
b100000 #
b100000 8
1%
#2200000
0%
#2210000
b100100 7
1%
#2220000
0%
#2230000
b1011 5
b1 ,
b10011 0
b1010 "
b1010 +
b1 /
b1010 )
b1 .
b1010000 *
b100 -
b0 4
b100 2
b1 1
b10000001000000010010011 '
b100100 #
b100100 8
1%
#2240000
0%
#2250000
b1100 5
b1011 $
b1011 6
b1011 )
b1011 "
b1011 +
b101000 7
1%
#2260000
0%
#2270000
b10 ,
b10 /
b10 .
b1100 *
b1 -
b1 2
b10 1
b1100110 5
b100010000000100010011 '
b1100100 )
b1100100 "
b1100100 +
b1100 $
b1100 6
b101000 #
b101000 8
1%
#2280000
0%
#2290000
b1101000 5
b1100110 $
b1100110 6
b1100110 )
b1100110 "
b1100110 +
b101100 7
1%
#2300000
0%
#2310000
b100 7
b11111111111111111111111111001010 ,
b1101111 0
b1010 /
b11111 .
bx *
b11001 -
b111 4
b1111110 3
b11111111111111111111111111011001 2
b11111111111111111111111111001010 1
b1101010 5
b11111101100111111111010101101111 '
bx )
b100 "
b100 +
b1101000 $
b1101000 6
b101100 #
b101100 8
1%
#2320000
0%
#2330000
b101100 ,
b1100011 0
b1100 /
b1100 )
b1 .
b1010000 *
b100 -
b0 4
b1 3
b100100 2
b101100 1
b1000 7
b10010000001000011001100011 '
b1101010 $
b1101010 6
b1100110 "
b1100110 +
b100 #
b100 8
1%
#2340000
0%
#2350000
b1100 5
b0 ,
b11 0
b110 /
b0 *
b0 -
b10 4
b0 3
b0 2
b110 1
b1100 7
b1010001100000011 '
b1011010 "
b1011010 +
b1000 #
b1000 8
1%
#2360000
0%
#2370000
b1101000 5
b111 /
b1101000 )
b10 .
b111 1
b10010001110000011 '
b1100 $
b1100 6
bx "
bx +
b1100 #
b1100 8
1%
#2380000
0%
#2390000
b1101000 $
b1101000 6
b10000 7
1%
#2400000
0%
#2410000
bx 5
b111 ,
b110011 0
bx )
b111 .
bx *
b111 -
b0 4
b111 2
b11100111000001110110011 '
b10000 #
b10000 8
1%
#2420000
0%
#2430000
bx $
bx 6
b10100 7
1%
#2440000
0%
#2450000
b10100 #
b10100 8
1%
#2460000
0%
#2470000
b11000 7
1%
#2480000
0%
#2490000
b11000 #
b11000 8
1%
#2500000
0%
#2510000
b11100 7
1%
#2520000
0%
#2530000
b1001 ,
b1001 /
b10100000 )
b11 .
b1001 1
b11100011000010010110011 '
b11100 #
b11100 8
1%
#2540000
0%
#2550000
b100000 7
1%
#2560000
0%
#2570000
b110 ,
b100011 0
b0 "
b0 +
b0 /
bx )
b1001 .
b11110 *
b110 -
b10 4
b110 2
b0 1
b11001001010000000100011 '
b100000 #
b100000 8
1%
#2580000
0%
#2590000
b100100 7
1%
#2600000
0%
#2610000
b1101 5
b1 ,
b10011 0
b1100 "
b1100 +
b1 /
b1100 )
b1 .
b1010000 *
b100 -
b0 4
b100 2
b1 1
b10000001000000010010011 '
b100100 #
b100100 8
1%
#2620000
0%
#2630000
b1110 5
b1101 )
b1101 "
b1101 +
b1101 $
b1101 6
b101000 7
1%
#2640000
0%
#2650000
b10 ,
b10 /
b10 .
b1110 *
b1 -
b1 2
b10 1
b1101010 5
b100010000000100010011 '
b1110 $
b1110 6
b1101000 )
b1101000 "
b1101000 +
b101000 #
b101000 8
1%
#2660000
0%
#2670000
b1101100 5
b1101010 )
b1101010 "
b1101010 +
b1101010 $
b1101010 6
b101100 7
1%
#2680000
0%
#2690000
b100 7
b11111111111111111111111111001010 ,
b1101111 0
b1010 /
b11111 .
bx *
b11001 -
b111 4
b1111110 3
b11111111111111111111111111011001 2
b11111111111111111111111111001010 1
b1101110 5
b11111101100111111111010101101111 '
b1101100 $
b1101100 6
bx )
b100 "
b100 +
b101100 #
b101100 8
1%
#2700000
0%
#2710000
b101100 ,
b1100011 0
b1100 /
b1110 )
b1 .
b1010000 *
b100 -
b0 4
b1 3
b100100 2
b101100 1
b1000 7
b10010000001000011001100011 '
b1101010 "
b1101010 +
b1101110 $
b1101110 6
b100 #
b100 8
1%
#2720000
0%
#2730000
b1110 5
b0 ,
b11 0
b110 /
b0 *
b0 -
b10 4
b0 3
b0 2
b110 1
b1100 7
b1010001100000011 '
b11110 "
b11110 +
b1000 #
b1000 8
1%
#2740000
0%
#2750000
b1101100 5
b111 /
b1101100 )
b10 .
b111 1
b10010001110000011 '
bx "
bx +
b1110 $
b1110 6
b1100 #
b1100 8
1%
#2760000
0%
#2770000
b1101100 $
b1101100 6
b10000 7
1%
#2780000
0%
#2790000
bx 5
b111 ,
b110011 0
bx )
b111 .
bx *
b111 -
b0 4
b111 2
b11100111000001110110011 '
b10000 #
b10000 8
1%
#2800000
0%
#2810000
bx $
bx 6
b10100 7
1%
#2820000
0%
#2830000
b10100 #
b10100 8
1%
#2840000
0%
#2850000
b11000 7
1%
#2860000
0%
#2870000
b11000 #
b11000 8
1%
#2880000
0%
#2890000
b11100 7
1%
#2900000
0%
#2910000
b1001 ,
b1001 /
b10100000 )
b11 .
b1001 1
b11100011000010010110011 '
b11100 #
b11100 8
1%
#2920000
0%
#2930000
b100000 7
1%
#2940000
0%
#2950000
b110 ,
b100011 0
b0 "
b0 +
b0 /
bx )
b1001 .
b1010 *
b110 -
b10 4
b110 2
b0 1
b11001001010000000100011 '
b100000 #
b100000 8
1%
#2960000
0%
#2970000
b100100 7
1%
#2980000
0%
#2990000
b1111 5
b1 ,
b10011 0
b1110 "
b1110 +
b1 /
b1110 )
b1 .
b1010000 *
b100 -
b0 4
b100 2
b1 1
b10000001000000010010011 '
b100100 #
b100100 8
1%
#3000000
0%
#3010000
b10000 5
b1111 $
b1111 6
b1111 )
b1111 "
b1111 +
b101000 7
1%
#3020000
0%
#3030000
b10 ,
b10 /
b10 .
b10000 *
b1 -
b1 2
b10 1
b1101110 5
b100010000000100010011 '
b1101100 )
b1101100 "
b1101100 +
b10000 $
b10000 6
b101000 #
b101000 8
1%
#3040000
0%
#3050000
b1110000 5
b1101110 $
b1101110 6
b1101110 )
b1101110 "
b1101110 +
b101100 7
1%
#3060000
0%
#3070000
b100 7
b11111111111111111111111111001010 ,
b1101111 0
b1010 /
b11111 .
bx *
b11001 -
b111 4
b1111110 3
b11111111111111111111111111011001 2
b11111111111111111111111111001010 1
b1110010 5
b11111101100111111111010101101111 '
bx )
b100 "
b100 +
b1110000 $
b1110000 6
b101100 #
b101100 8
1%
#3080000
0%
