2x2/bilg org/odev2/q1/riscv.v
module testbench;
	reg clk;
	reg reset;
	wire [31:0] writedata;
	wire [31:0] dataadr;
	wire memwrite;
	top dut(
		.clk(clk),
		.reset(reset),
		.writedata(writedata),
		.dataadr(dataadr),
		.memwrite(memwrite)
	);
	initial begin
		reset <= 1;
		#(22)
			;
		reset <= 0;
	end
	always begin
		clk <= 1;
		#(5)
			;
		clk <= 0;
		#(5)
			;
	end

	always@(negedge clk)
    begin
      if(memwrite) begin
        if(dataadr === 84 & writedata === 7) begin
          $display("Simulation succeeded");
          $stop;
        end else if (dataadr !== 80) begin
          $display("Simulation failed");
          $stop;
        end
      end
    end
	initial begin  
		$dumpfile("test_tb.vcd");
		$dumpvars(0,testbench);
	end   

endmodule
module top (
	clk,
	reset,
	writedata,
	dataadr,
	memwrite
);
	input clk;
	input reset;
	output wire [31:0] writedata;
	output wire [31:0] dataadr;
	output wire memwrite;
	wire [31:0] pc;
	wire [31:0] instr;
	wire [31:0] readdata;
	riscv riscv(
		.clk(clk),
		.reset(reset),
		.pc(pc),
		.instr(instr),
		.memwrite(memwrite),
		.aluout(dataadr),
		.writedata(writedata),
		.readdata(readdata)
	);
	imem imem(
		.a(pc[7:2]),
		.rd(instr)
	);
	dmem dmem(
		.clk(clk),
		.we(memwrite),
		.a(dataadr),
		.wd(writedata),
		.rd(readdata)
	);
endmodule
module riscv (
	clk,
	reset,
	pc,
	instr,
	memwrite,
	aluout,
	writedata,
	readdata
);
	input clk;
	input reset;
	output wire [31:0] pc;
	input [31:0] instr;
	output wire memwrite;
	output wire [31:0] aluout;
	output wire [31:0] writedata;
	output wire [1:0] aluop;
	input [31:0] readdata;
	wire regwrite;
	wire [1:0] immsrc;
	wire branch;
	wire alusrc;
	wire [1:0] resultsrc;
	wire jump;
	wire [2:0] alucontrol;
	wire zero;
	wire pcsrc;
	controller c(
		.op(instr[6:0]),
		.funct3(instr[14:12]),
		.funct7(instr[30]),
		.zero(zero),
		.regwrite(regwrite),
		.immsrc(immsrc),
		.branch(branch),
		.alusrc(alusrc),
		.memwrite(memwrite),
		.resultsrc(resultsrc),
		.jump(jump),
		.aluop(aluop),
		.alucontrol(alucontrol),
		.pcsrc(pcsrc)
	);
	datapath dp(
		.clk(clk),
		.reset(reset),
		.pcsrc(pcsrc),
		.alusrc(alusrc),
		.regwrite(regwrite),
		.jump(jump),
		.alucontrol(alucontrol),
		.zero(zero),
		.pc(pc),
		.instr(instr),
		.aluout(aluout),
		.writedata(writedata),
		.readdata(readdata),
		.resultsrc(resultsrc),
		.immsrc(immsrc)
	);
endmodule
module controller (
	op,
	funct3,
	funct7,
	zero,
	regwrite,
	immsrc,
	branch,
	alusrc,
	memwrite,
	resultsrc,
	jump,
	aluop,
	alucontrol,
	pcsrc
);
	input [6:0] op;
	input [2:0] funct3;
	input funct7;
	input zero;
	output wire regwrite;
	output wire [1:0] immsrc;
	output wire branch;
	output wire alusrc;
	output wire memwrite;
	output wire [1:0] resultsrc;
	output wire jump;
	output wire [2:0] alucontrol;
	output wire [1:0] aluop;
	output pcsrc;
	maindec md(
		.op(op),
		.regwrite(regwrite),
		.immsrc(immsrc),
		.branch(branch),
		.alusrc(alusrc),
		.memwrite(memwrite),
		.resultsrc(resultsrc),
		.jump(jump),
		.aluop(aluop)
	);
	aludec ad(
		.funct7(funct7),
		.funct3(funct3),
		.op5(op[5]),
		.aluop(aluop),
		.alucontrol(alucontrol)
	);
	/*assign pcsrc = (branch & zero) | jump;*/
	assign pcsrc = (branch & zero) | jump;
endmodule
module maindec (
	op,
	regwrite,
	immsrc,
	branch,
	alusrc,
	memwrite,
	resultsrc,
	jump,
	aluop
);
	input [6:0] op;
	output wire regwrite;
	output wire [1:0] immsrc;
	output wire branch;
	output wire alusrc;
	output wire memwrite;
	output wire [1:0] resultsrc;
	output wire jump;
	output wire [1:0] aluop;
	reg [10:0] controls;
	assign {regwrite, immsrc, alusrc, memwrite, resultsrc, branch, aluop, jump} = controls;
	always @(*)
		case (op)
			7'b0000011 : controls <= 11'b10010010000; // lw
			7'b0100011 : controls <= 11'b00111xx0000; // sw
			7'b0110011 : controls <= 11'b1xx00000100; // R
			7'b1100011 : controls <= 11'b01000xx1010; // beq
			7'b0010011 : controls <= 11'b10010000100; // i type
			7'b1101111 : controls <= 11'b111x0100xx1; // jal
			default : controls    <= 11'bxxxxxxxxxxx;
		endcase
endmodule
module aludec (
	funct3,
	funct7,
	aluop,
	alucontrol,
	op5
);
	input [2:0] funct3;
	input funct7;
	input [1:0] aluop;
	input op5;
	output reg [2:0] alucontrol;
	always @(*)
		case (aluop)
			2'b00: alucontrol <= 3'b000;
			2'b01: alucontrol <= 3'b001;
			default:
				case (funct3)
					3'b000: alucontrol <= ((op5 & funct7) ? 3'b001 : 3'b000);
					3'b010: alucontrol <= 3'b101;
					3'b110: alucontrol <= 3'b011;
					3'b111: alucontrol <= 3'b010;
					default: alucontrol <= 3'bxxx;
				endcase
		endcase
endmodule
module datapath (
	clk,
	reset,
	pcsrc,
	alusrc,
	regwrite,
	jump,
	alucontrol,
	zero,
	pc,
	instr,
	aluout,
	writedata,
	readdata,
	resultsrc,
	immsrc
);
	input clk;
	input reset;
	input pcsrc;
	input alusrc;
	input regwrite;
	input [1:0] resultsrc;
	input jump;
	input [2:0] alucontrol;
	output wire zero;
	output wire [31:0] pc;
	input [31:0] instr;
	output wire [31:0] aluout;
	output wire [31:0] writedata;
	input [31:0] readdata;
	input [1:0] immsrc;
	wire [4:0] writereg;
	wire [31:0] pcnext;
	wire [31:0] pcnextbr;
	wire [31:0] pcplus4;
	wire [31:0] pctarget;
	wire [31:0] signimm;
	wire [31:0] signimmsh;
	wire [31:0] srca;
	wire [31:0] srcb;
	wire [31:0] result;
	flopr #(.WIDTH(32)) pcreg(
		.clk(clk),
		.reset(reset),
		.d(pcnext),
		.q(pc)
	);
	adder pcadd1(
		.a(pc),
		.b(32'b00000000000000000000000000000100),
		.y(pcplus4)
	);

	adder pcadd2(
		.a(pc),
		.b(signimm),
		.y(pctarget)
	);
	mux2 #(.WIDTH(32)) pcbrmux(
		.d0(pcplus4),
		.d1(pctarget),
		.s(pcsrc),
		.y(pcnext)
	);
	/*mux2 #(.WIDTH(32)) pcmux(
		.d0(pcnextbr),
		.d1({pcplus4[31:28], instr[25:0], 2'b00}),
		.s(jump),
		.y(pcnext)
	);*/
	regfile rf(
		.clk(clk),
		.we3(regwrite),
		.ra1(instr[19:15]),
		.ra2(instr[24:20]),
		.wa3(instr[11:7]),
		.wd3(result),
		.rd1(srca),
		.rd2(writedata)
	);

	mux4 #(.WIDTH(32)) resmux(
		.d0(aluout),
		.d1(readdata),
		.d2(pcplus4),
		.d3(32'b00000000000000000000000000000000),
		.s(resultsrc),
		.y(result)
	);
	signext se(
		.a(instr),
		.immsrc(immsrc),
		.y(signimm)
	);
	mux2 #(.WIDTH(32)) srcbmux(
		.d0(writedata),
		.d1(signimm),
		.s(alusrc),
		.y(srcb)
	);
	alu alu(
		.a(srca),
		.b(srcb),
		.alucont(alucontrol),
		.result(aluout),
		.zero(zero)
	);
endmodule
module dmem (
	clk,
	we,
	a,
	wd,
	rd
);
	input clk;
	input we;
	input [31:0] a;
	input [31:0] wd;
	output wire [31:0] rd;
	reg [31:0] RAM [63:0];
	assign rd = RAM[a[31:2]];
	always @(posedge clk)
		if (we)
			RAM[a[31:2]] <= wd;
endmodule
module imem (
	a,
	rd
);
	input [5:0] a;
	output wire [31:0] rd;
	reg [31:0] RAM [63:0];
	initial $readmemh("memfile.dat", RAM);
	assign rd = RAM[a];
endmodule
module alu (
	a,
	b,
	alucont,
	result,
	zero
);
	input [31:0] a;
	input [31:0] b;
	input [2:0] alucont;
	output reg [31:0] result;
	output wire zero;
	wire [31:0] b2;
	wire [31:0] sum;
	wire [31:0] slt;
	assign b2 = (alucont[0] ? ~b : b);
	assign sum = (a + b2) + alucont[0];
	assign slt = sum[31];
	always @(*)
		case (alucont[2:0])
			3'b010: result <= a & b;
			3'b011: result <= a | b;
			3'b000: result <= sum;
			3'b001: result <= sum;
			3'b101: result <= slt;
		endcase
	assign zero = (result == 32'b00000000000000000000000000000000);
endmodule
module regfile (
	clk,
	we3,
	ra1,
	ra2,
	wa3,
	wd3,
	rd1,
	rd2
);
	input clk;
	input we3;
	input [4:0] ra1;
	input [4:0] ra2;
	input [4:0] wa3;
	input [31:0] wd3;
	output wire [31:0] rd1;
	output wire [31:0] rd2;
	reg [31:0] rf [31:0];
	always @(posedge clk)
		if (we3)
			rf[wa3] <= wd3;
	assign rd1 = (ra1 != 0 ? rf[ra1] : 0);
	assign rd2 = (ra2 != 0 ? rf[ra2] : 0);
endmodule
module adder (
	a,
	b,
	y
);
	input [31:0] a;
	input [31:0] b;
	output wire [31:0] y;
	assign y = a + b;
endmodule
module sl2 (
	a,
	y
);
	input [31:0] a;
	output wire [31:0] y;
	assign y = {a[29:0], 2'b00};
endmodule
module signext (
	a,
	immsrc,
	y
);
	input [31:0] a;
	input [1:0] immsrc;
	output reg [31:0] y;
	always @(*)
		begin
			case(immsrc)
				2'b00: y <= {{20{a[31]}}, a[31:20]};
				2'b01: y <= {{20{a[31]}}, a[31:25], a[11:7]};
				2'b10: y<={{20{a[31]}}, a[7], a[30:25], a[11:8], {1'b0}};
				2'b11: y<={{12{a[31]}}, a[19:12], a[20], a[30:21], {1'b0}};
				default:  y<=1'b0;
			endcase
		end
endmodule
module flopr (
	clk,
	reset,
	d,
	q
);
	parameter WIDTH = 8;
	input clk;
	input reset;
	input [WIDTH - 1:0] d;
	output reg [WIDTH - 1:0] q;
	always @(posedge clk or posedge reset)
		if (reset)
			q <= 0;
		else
			q <= d;
endmodule
module flopenr (
	clk,
	reset,
	en,
	d,
	q
);
	parameter WIDTH = 8;
	input clk;
	input reset;
	input en;
	input [WIDTH - 1:0] d;
	output reg [WIDTH - 1:0] q;
	always @(posedge clk or posedge reset)
		if (reset)
			q <= 0;
		else if (en)
			q <= d;
endmodule
module mux2 (
	d0,
	d1,
	s,
	y
);
	parameter WIDTH = 8;
	input [WIDTH - 1:0] d0;
	input [WIDTH - 1:0] d1;
	input s;
	output wire [WIDTH - 1:0] y;
	assign y = (s ? d1 : d0);
endmodule


module mux4 (
	d0,
	d1,
	d2,
	d3,
	s,
	y
);
	parameter WIDTH = 8;
	input [WIDTH - 1:0] d0;
	input [WIDTH - 1:0] d1;
	input [WIDTH - 1:0] d2;
	input [WIDTH - 1:0] d3;
	input [1:0] s;
	output reg [WIDTH - 1:0] y;
	always @(*)
		begin
			case(s)
				2'b00: y<=d0;
				2'b01: y<=d1;
				2'b10: y<=d2;
				2'b11: y<=d3;
				default:  y<=1'b0;
			endcase
		end
endmodule

2x2/bilg org/odev2/q1/test_tb.vcd
$date
	Tue Apr 30 22:07:24 2024
$end
$version
	Icarus Verilog
$end
$timescale
	1s
$end
$scope module testbench $end
$var wire 32 ! writedata [31:0] $end
$var wire 1 " memwrite $end
$var wire 32 # dataadr [31:0] $end
$var reg 1 $ clk $end
$var reg 1 % reset $end
$scope module dut $end
$var wire 1 $ clk $end
$var wire 1 % reset $end
$var wire 32 & writedata [31:0] $end
$var wire 32 ' readdata [31:0] $end
$var wire 32 ( pc [31:0] $end
$var wire 1 " memwrite $end
$var wire 32 ) instr [31:0] $end
$var wire 32 * dataadr [31:0] $end
$scope module dmem $end
$var wire 1 $ clk $end
$var wire 32 + rd [31:0] $end
$var wire 1 " we $end
$var wire 32 , wd [31:0] $end
$var wire 32 - a [31:0] $end
$upscope $end
$scope module imem $end
$var wire 6 . a [5:0] $end
$var wire 32 / rd [31:0] $end
$upscope $end
$scope module riscv $end
$var wire 1 $ clk $end
$var wire 32 0 instr [31:0] $end
$var wire 32 1 readdata [31:0] $end
$var wire 1 % reset $end
$var wire 1 2 zero $end
$var wire 32 3 writedata [31:0] $end
$var wire 2 4 resultsrc [1:0] $end
$var wire 1 5 regwrite $end
$var wire 1 6 pcsrc $end
$var wire 32 7 pc [31:0] $end
$var wire 1 " memwrite $end
$var wire 1 8 jump $end
$var wire 2 9 immsrc [1:0] $end
$var wire 1 : branch $end
$var wire 1 ; alusrc $end
$var wire 32 < aluout [31:0] $end
$var wire 2 = aluop [1:0] $end
$var wire 3 > alucontrol [2:0] $end
$scope module c $end
$var wire 3 ? funct3 [2:0] $end
$var wire 1 @ funct7 $end
$var wire 7 A op [6:0] $end
$var wire 1 6 pcsrc $end
$var wire 1 2 zero $end
$var wire 2 B resultsrc [1:0] $end
$var wire 1 5 regwrite $end
$var wire 1 " memwrite $end
$var wire 1 8 jump $end
$var wire 2 C immsrc [1:0] $end
$var wire 1 : branch $end
$var wire 1 ; alusrc $end
$var wire 2 D aluop [1:0] $end
$var wire 3 E alucontrol [2:0] $end
$scope module ad $end
$var wire 3 F funct3 [2:0] $end
$var wire 1 @ funct7 $end
$var wire 1 G op5 $end
$var wire 2 H aluop [1:0] $end
$var reg 3 I alucontrol [2:0] $end
$upscope $end
$scope module md $end
$var wire 7 J op [6:0] $end
$var wire 2 K resultsrc [1:0] $end
$var wire 1 5 regwrite $end
$var wire 1 " memwrite $end
$var wire 1 8 jump $end
$var wire 2 L immsrc [1:0] $end
$var wire 1 : branch $end
$var wire 1 ; alusrc $end
$var wire 2 M aluop [1:0] $end
$var reg 11 N controls [10:0] $end
$upscope $end
$upscope $end
$scope module dp $end
$var wire 3 O alucontrol [2:0] $end
$var wire 1 ; alusrc $end
$var wire 1 $ clk $end
$var wire 2 P immsrc [1:0] $end
$var wire 32 Q instr [31:0] $end
$var wire 1 8 jump $end
$var wire 1 6 pcsrc $end
$var wire 32 R readdata [31:0] $end
$var wire 1 5 regwrite $end
$var wire 1 % reset $end
$var wire 2 S resultsrc [1:0] $end
$var wire 1 2 zero $end
$var wire 32 T writedata [31:0] $end
$var wire 32 U srcb [31:0] $end
$var wire 32 V srca [31:0] $end
$var wire 32 W signimm [31:0] $end
$var wire 32 X result [31:0] $end
$var wire 32 Y pctarget [31:0] $end
$var wire 32 Z pcplus4 [31:0] $end
$var wire 32 [ pcnext [31:0] $end
$var wire 32 \ pc [31:0] $end
$var wire 32 ] aluout [31:0] $end
$scope module alu $end
$var wire 3 ^ alucont [2:0] $end
$var wire 1 2 zero $end
$var wire 32 _ sum [31:0] $end
$var wire 32 ` slt [31:0] $end
$var wire 32 a b2 [31:0] $end
$var wire 32 b b [31:0] $end
$var wire 32 c a [31:0] $end
$var reg 32 d result [31:0] $end
$upscope $end
$scope module pcadd1 $end
$var wire 32 e b [31:0] $end
$var wire 32 f y [31:0] $end
$var wire 32 g a [31:0] $end
$upscope $end
$scope module pcadd2 $end
$var wire 32 h y [31:0] $end
$var wire 32 i b [31:0] $end
$var wire 32 j a [31:0] $end
$upscope $end
$scope module pcbrmux $end
$var wire 32 k d0 [31:0] $end
$var wire 32 l d1 [31:0] $end
$var wire 1 6 s $end
$var wire 32 m y [31:0] $end
$var parameter 32 n WIDTH $end
$upscope $end
$scope module pcreg $end
$var wire 1 $ clk $end
$var wire 32 o d [31:0] $end
$var wire 1 % reset $end
$var parameter 32 p WIDTH $end
$var reg 32 q q [31:0] $end
$upscope $end
$scope module resmux $end
$var wire 32 r d0 [31:0] $end
$var wire 32 s d1 [31:0] $end
$var wire 32 t d2 [31:0] $end
$var wire 32 u d3 [31:0] $end
$var wire 2 v s [1:0] $end
$var parameter 32 w WIDTH $end
$var reg 32 x y [31:0] $end
$upscope $end
$scope module rf $end
$var wire 1 $ clk $end
$var wire 5 y ra1 [4:0] $end
$var wire 5 z ra2 [4:0] $end
$var wire 5 { wa3 [4:0] $end
$var wire 32 | wd3 [31:0] $end
$var wire 1 5 we3 $end
$var wire 32 } rd2 [31:0] $end
$var wire 32 ~ rd1 [31:0] $end
$upscope $end
$scope module se $end
$var wire 32 !" a [31:0] $end
$var wire 2 "" immsrc [1:0] $end
$var reg 32 #" y [31:0] $end
$upscope $end
$scope module srcbmux $end
$var wire 32 $" d0 [31:0] $end
$var wire 32 %" d1 [31:0] $end
$var wire 1 ; s $end
$var wire 32 &" y [31:0] $end
$var parameter 32 '" WIDTH $end
$upscope $end
$upscope $end
$upscope $end
$upscope $end
$upscope $end
$enddefinitions $end
$comment Show the parameter values. $end
$dumpall
b100000 '"
b100000 w
b100000 p
b100000 n
$end
#0
$dumpvars
b101 &"
b101 %"
bx $"
b101 #"
b0 ""
b10100000000000100010011 !"
b0 ~
bx }
b101 |
b10 {
b101 z
b0 y
b101 x
b0 v
b0 u
b100 t
bx s
b101 r
b0 q
b100 o
b100 m
b101 l
b100 k
b0 j
b101 i
b101 h
b0 g
b100 f
b100 e
b101 d
b0 c
b101 b
b101 a
b0 `
b101 _
b0 ^
b101 ]
b0 \
b100 [
b100 Z
b101 Y
b101 X
b101 W
b0 V
b101 U
bx T
b0 S
bx R
b10100000000000100010011 Q
b0 P
b0 O
b10010000100 N
b10 M
b0 L
b0 K
b10011 J
b0 I
b10 H
0G
b0 F
b0 E
b10 D
b0 C
b0 B
b10011 A
0@
b0 ?
b0 >
b10 =
b101 <
1;
0:
b0 9
08
b0 7
06
15
b0 4
bx 3
02
bx 1
b10100000000000100010011 0
b10100000000000100010011 /
b0 .
b101 -
bx ,
bx +
b101 *
b10100000000000100010011 )
b0 (
bx '
bx &
1%
1$
b101 #
0"
bx !
$end
#5
0$
#10
1$
#15
0$
#20
1$
#22
0%
#25
0$
#30
b1100 X
b1100 x
b1100 |
b1100 #
b1100 *
b1100 -
b1100 <
b1100 ]
b1100 d
b1100 r
b1100 _
b1100 a
b1100 U
b1100 b
b1100 &"
b1100 W
b1100 i
b1100 #"
b1100 %"
b1100 z
b11 {
b1000 [
b1000 m
b1000 o
b110000000000000110010011 )
b110000000000000110010011 /
b110000000000000110010011 0
b110000000000000110010011 Q
b110000000000000110010011 !"
b1 .
b10000 Y
b10000 h
b10000 l
b1000 Z
b1000 f
b1000 k
b1000 t
b100 (
b100 7
b100 \
b100 g
b100 j
b100 q
1$
#35
0$
#40
b11 X
b11 x
b11 |
b11111111111111111111111111110111 a
b11111111111111111111111111110111 U
b11111111111111111111111111110111 b
b11111111111111111111111111110111 &"
b11 #
b11 *
b11 -
b11 <
b11 ]
b11 d
b11 r
b11111111111111111111111111110111 W
b11111111111111111111111111110111 i
b11111111111111111111111111110111 #"
b11111111111111111111111111110111 %"
b11 _
b1100 V
b1100 c
b1100 ~
1@
b11 y
b10111 z
b111 {
b1100 [
b1100 m
b1100 o
b11111111011100011000001110010011 )
b11111111011100011000001110010011 /
b11111111011100011000001110010011 0
b11111111011100011000001110010011 Q
b11111111011100011000001110010011 !"
b10 .
b11111111111111111111111111111111 Y
b11111111111111111111111111111111 h
b11111111111111111111111111111111 l
b1100 Z
b1100 f
b1100 k
b1100 t
b1000 (
b1000 7
b1000 \
b1000 g
b1000 j
b1000 q
1$
#45
0$
#50
b111 X
b111 x
b111 |
b11111111111111111111111111111010 a
bx 9
bx C
bx L
bx P
bx ""
0;
b101 U
b101 b
b101 &"
b111 #
b111 *
b111 -
b111 <
b111 ]
b111 d
b111 r
b1xx00000100 N
b11 >
b11 E
b11 I
b11 O
b11 ^
b0 W
b0 i
b0 #"
b0 %"
b1 `
1G
b11111111111111111111111111111110 _
b11 V
b11 c
b11 ~
b101 !
b101 &
b101 ,
b101 3
b101 T
b101 }
b101 $"
b110011 A
b110011 J
b110 ?
b110 F
0@
b111 y
b10 z
b100 {
b10000 [
b10000 m
b10000 o
b1000111110001000110011 )
b1000111110001000110011 /
b1000111110001000110011 0
b1000111110001000110011 Q
b1000111110001000110011 !"
b11 .
b1100 Y
b1100 h
b1100 l
b10000 Z
b10000 f
b10000 k
b10000 t
b1100 (
b1100 7
b1100 \
b1100 g
b1100 j
b1100 q
1$
#55
0$
#60
b100 X
b100 x
b100 |
b100 #
b100 *
b100 -
b100 <
b100 ]
b100 d
b100 r
b10 >
b10 E
b10 I
b10 O
b10 ^
b111 a
b0 `
b111 U
b111 b
b111 &"
b10011 _
b1100 V
b1100 c
b1100 ~
b111 !
b111 &
b111 ,
b111 3
b111 T
b111 }
b111 $"
b111 ?
b111 F
b11 y
b100 z
b101 {
b10100 [
b10100 m
b10100 o
b10000011111001010110011 )
b10000011111001010110011 /
b10000011111001010110011 0
b10000011111001010110011 Q
b10000011111001010110011 !"
b100 .
b10000 Y
b10000 h
b10000 l
b10100 Z
b10100 f
b10100 k
b10100 t
b10000 (
b10000 7
b10000 \
b10000 g
b10000 j
b10000 q
1$
#65
0$
#70
b1011 X
b1011 x
b1011 |
b1011 #
b1011 *
b1011 -
b1011 <
b1011 ]
b1011 d
b1011 r
b0 >
b0 E
b0 I
b0 O
b0 ^
b1011 _
b100 V
b100 c
b100 ~
b0 ?
b0 F
b101 y
b11000 [
b11000 m
b11000 o
b10000101000001010110011 )
b10000101000001010110011 /
b10000101000001010110011 0
b10000101000001010110011 Q
b10000101000001010110011 !"
b101 .
b10100 Y
b10100 h
b10100 l
b11000 Z
b11000 f
b11000 k
b11000 t
b10100 (
b10100 7
b10100 \
b10100 g
b10100 j
b10100 q
1$
#75
0$
#80
b101100 W
b101100 i
b101100 #"
b101100 %"
b1 >
b1 E
b1 I
b1 O
b1 ^
b0 X
b0 x
b0 |
05
b10 9
b10 C
b10 L
b10 P
b10 ""
bx 4
bx B
bx K
bx S
bx v
1:
b1 =
b1 D
b1 H
b1 M
b1000xx1010 N
b1000 #
b1000 *
b1000 -
b1000 <
b1000 ]
b1000 d
b1000 r
b11111111111111111111111111111100 a
b11 U
b11 b
b11 &"
b11 !
b11 &
b11 ,
b11 3
b11 T
b11 }
b11 $"
b1100011 A
b1100011 J
b111 z
b1100 {
b1000 _
b1011 V
b1011 c
b1011 ~
b11100 [
b11100 m
b11100 o
b10011100101000011001100011 )
b10011100101000011001100011 /
b10011100101000011001100011 0
b10011100101000011001100011 Q
b10011100101000011001100011 !"
b110 .
b1000100 Y
b1000100 h
b1000100 l
b11100 Z
b11100 f
b11100 k
b11100 t
b11000 (
b11000 7
b11000 \
b11000 g
b11000 j
b11000 q
1$
#85
0$
#90
12
b101 >
b101 E
b101 I
b101 O
b101 ^
b0 X
b0 x
b0 |
15
bx 9
bx C
bx L
bx P
bx ""
b0 4
b0 B
b0 K
b0 S
b0 v
0:
b10 =
b10 D
b10 H
b10 M
b0 #
b0 *
b0 -
b0 <
b0 ]
b0 d
b0 r
b1xx00000100 N
b0 W
b0 i
b0 #"
b0 %"
b11111111111111111111111111111000 a
b111 U
b111 b
b111 &"
b101 _
b1100 V
b1100 c
b1100 ~
b111 !
b111 &
b111 ,
b111 3
b111 T
b111 }
b111 $"
b110011 A
b110011 J
b10 ?
b10 F
b11 y
b100 z
b100 {
b100000 [
b100000 m
b100000 o
b10000011010001000110011 )
b10000011010001000110011 /
b10000011010001000110011 0
b10000011010001000110011 Q
b10000011010001000110011 !"
b111 .
b11100 Y
b11100 h
b11100 l
b100000 Z
b100000 f
b100000 k
b100000 t
b11100 (
b11100 7
b11100 \
b11100 g
b11100 j
b11100 q
1$
#95
0$
#100
b1000 W
b1000 i
b1000 #"
b1000 %"
16
05
b10 9
b10 C
b10 L
b10 P
b10 ""
bx 4
bx B
bx K
bx S
bx v
1:
b1 =
b1 D
b1 H
b1 M
12
b0 #
b0 *
b0 -
b0 <
b0 ]
b0 d
b0 r
b1000xx1010 N
b1 >
b1 E
b1 I
b1 O
b1 ^
b11111111111111111111111111111111 a
b0 `
b0 _
b0 V
b0 c
b0 ~
b0 U
b0 b
b0 &"
b1100011 A
b1100011 J
b0 ?
b0 F
b100 y
b0 z
b1000 {
b0 !
b0 &
b0 ,
b0 3
b0 T
b0 }
b0 $"
b101000 [
b101000 m
b101000 o
b100000010001100011 )
b100000010001100011 /
b100000010001100011 0
b100000010001100011 Q
b100000010001100011 !"
b1000 .
b101000 Y
b101000 h
b101000 l
b100100 Z
b100100 f
b100100 k
b100100 t
b100000 (
b100000 7
b100000 \
b100000 g
b100000 j
b100000 q
1$
#105
0$
#110
b101 >
b101 E
b101 I
b101 O
b101 ^
b1 X
b1 x
b1 |
06
15
bx 9
bx C
bx L
bx P
bx ""
b0 4
b0 B
b0 K
b0 S
b0 v
0:
b10 =
b10 D
b10 H
b10 M
02
b1 #
b1 *
b1 -
b1 <
b1 ]
b1 d
b1 r
b1xx00000100 N
b0 W
b0 i
b0 #"
b0 %"
b1 `
b11111111111111111111111111111010 a
b101 U
b101 b
b101 &"
b11111111111111111111111111111110 _
b11 V
b11 c
b11 ~
b101 !
b101 &
b101 ,
b101 3
b101 T
b101 }
b101 $"
b110011 A
b110011 J
b10 ?
b10 F
b111 y
b10 z
b100 {
b101100 [
b101100 m
b101100 o
b1000111010001000110011 )
b1000111010001000110011 /
b1000111010001000110011 0
b1000111010001000110011 Q
b1000111010001000110011 !"
b1010 .
b101000 Y
b101000 h
b101000 l
b101100 Z
b101100 f
b101100 k
b101100 t
b101000 (
b101000 7
b101000 \
b101000 g
b101000 j
b101000 q
1$
#115
0$
#120
b1100 X
b1100 x
b1100 |
b1100 #
b1100 *
b1100 -
b1100 <
b1100 ]
b1100 d
b1100 r
b0 `
b0 >
b0 E
b0 I
b0 O
b0 ^
b1011 a
b1011 U
b1011 b
b1011 &"
b1100 _
b1 V
b1 c
b1 ~
b1011 !
b1011 &
b1011 ,
b1011 3
b1011 T
b1011 }
b1011 $"
b0 ?
b0 F
b100 y
b101 z
b111 {
b110000 [
b110000 m
b110000 o
b10100100000001110110011 )
b10100100000001110110011 /
b10100100000001110110011 0
b10100100000001110110011 Q
b10100100000001110110011 !"
b1011 .
b101100 Y
b101100 h
b101100 l
b110000 Z
b110000 f
b110000 k
b110000 t
b101100 (
b101100 7
b101100 \
b101100 g
b101100 j
b101100 q
1$
#125
0$
#130
b111 X
b111 x
b111 |
b111 #
b111 *
b111 -
b111 <
b111 ]
b111 d
b111 r
b1 >
b1 E
b1 I
b1 O
b1 ^
b11111111111111111111111111111010 a
b101 U
b101 b
b101 &"
b111 _
b1100 V
b1100 c
b1100 ~
b101 !
b101 &
b101 ,
b101 3
b101 T
b101 }
b101 $"
1@
b111 y
b10 z
b110100 [
b110100 m
b110100 o
b1000000001000111000001110110011 )
b1000000001000111000001110110011 /
b1000000001000111000001110110011 0
b1000000001000111000001110110011 Q
b1000000001000111000001110110011 !"
b1100 .
b110000 Y
b110000 h
b110000 l
b110100 Z
b110100 f
b110100 k
b110100 t
b110000 (
b110000 7
b110000 \
b110000 g
b110000 j
b110000 q
1$
#135
0$
#140
b1000100 W
b1000100 i
b1000100 #"
b1000100 %"
02
b0 X
b0 x
b0 |
05
b1 9
b1 C
b1 L
b1 P
b1 ""
1;
1"
bx 4
bx B
bx K
bx S
bx v
b0 =
b0 D
b0 H
b0 M
b111xx0000 N
b0 >
b0 E
b0 I
b0 O
b0 ^
b1010000 #
b1010000 *
b1010000 -
b1010000 <
b1010000 ]
b1010000 d
b1010000 r
b1000100 a
b1000100 U
b1000100 b
b1000100 &"
b111 !
b111 &
b111 ,
b111 3
b111 T
b111 }
b111 $"
b100011 A
b100011 J
b10 ?
b10 F
0@
b11 y
b111 z
b100 {
b1010000 _
b1100 V
b1100 c
b1100 ~
b111000 [
b111000 m
b111000 o
b100011100011010001000100011 )
b100011100011010001000100011 /
b100011100011010001000100011 0
b100011100011010001000100011 Q
b100011100011010001000100011 !"
b1101 .
b1111000 Y
b1111000 h
b1111000 l
b111000 Z
b111000 f
b111000 k
b111000 t
b110100 (
b110100 7
b110100 \
b110100 g
b110100 j
b110100 q
1$
#145
0$
#150
b111 X
b111 x
b111 |
b1010000 a
15
b0 9
b0 C
b0 L
b0 P
b0 ""
0"
b1 4
b1 B
b1 K
b1 S
b1 v
b1010000 U
b1010000 b
b1010000 &"
b1010000 #
b1010000 *
b1010000 -
b1010000 <
b1010000 ]
b1010000 d
b1010000 r
b10010010000 N
b1010000 W
b1010000 i
b1010000 #"
b1010000 %"
0G
b1010000 _
b0 V
b0 c
b0 ~
bx !
bx &
bx ,
bx 3
bx T
bx }
bx $"
b11 A
b11 J
b0 y
b10000 z
b10 {
b111100 [
b111100 m
b111100 o
b101000000000010000100000011 )
b101000000000010000100000011 /
b101000000000010000100000011 0
b101000000000010000100000011 Q
b101000000000010000100000011 !"
b1110 .
b111 '
b111 +
b111 1
b111 R
b111 s
b10001000 Y
b10001000 h
b10001000 l
b111100 Z
b111100 f
b111100 k
b111100 t
b111000 (
b111000 7
b111000 \
b111000 g
b111000 j
b111000 q
1$
#155
0$
#160
bx '
bx +
bx 1
bx R
bx s
x2
bx #
bx *
bx -
bx <
bx ]
bx d
bx r
b1000000 X
b1000000 x
b1000000 |
b0x `
16
bx _
bx a
b11 9
b11 C
b11 L
b11 P
b11 ""
x;
b10 4
b10 B
b10 K
b10 S
b10 v
bx =
bx D
bx H
bx M
18
bx U
bx b
bx &"
b111x0100xx1 N
b1000 W
b1000 i
b1000 #"
b1000 %"
1G
b1101111 A
b1101111 J
b0 ?
b0 F
b1000 z
b0 {
b1000100 [
b1000100 m
b1000100 o
b100000000000000001101111 )
b100000000000000001101111 /
b100000000000000001101111 0
b100000000000000001101111 Q
b100000000000000001101111 !"
b1111 .
b1000100 Y
b1000100 h
b1000100 l
b1000000 Z
b1000000 f
b1000000 k
b1000000 t
b111100 (
b111100 7
b111100 \
b111100 g
b111100 j
b111100 q
1$
#165
0$
